setup.py
client/__init__.py
client/client.py
client/decors.py
client/descr.py
client/errors.py
client/meta.py
client/client/__init__.py
client/client/add_contact.py
client/client/database.py
client/client/del_contact.py
client/client/main_window.py
client/client/main_window_conv.py
client/client/start_dialog.py
client/client/transport.py
client/general/__init__.py
client/general/utils.py
client/general/variables.py
client/logs/__init__.py
client/logs/configs/__init__.py
client/logs/configs/config_client_log.py
client/logs/configs/config_server_log.py
client/project_unittests/__init__.py
client/project_unittests/test_client.py
client/project_unittests/test_server.py
client/project_unittests/test_utils.py
messenger_client_yury777.egg-info/PKG-INFO
messenger_client_yury777.egg-info/SOURCES.txt
messenger_client_yury777.egg-info/dependency_links.txt
messenger_client_yury777.egg-info/requires.txt
messenger_client_yury777.egg-info/top_level.txt