Metadata-Version: 1.0
Name: messenger-client-yury777
Version: 0.1
Summary: messenger_client
Home-page: UNKNOWN
Author: Yury Kim
Author-email: kimkrk84@mail.ru
License: UNKNOWN
Platform: UNKNOWN
